invopt/__init__.py
invopt/main.py
invopt-0.0.7.dist-info/LICENSE.txt
invopt-0.0.7.dist-info/METADATA
invopt-0.0.7.dist-info/WHEEL
invopt-0.0.7.dist-info/top_level.txt
invopt-0.0.7.dist-info/RECORD
